{
    "chain_name": "Allora Edgenet",
    "api": [
        {
            "address": "https://allora-testnet-api.itrocket.net", 
            "provider": "Allora Testnet"
        }
    ], 
    "rpc": [
        {
            "address": "https://allora-rpc.testnet.allora.network", 
            "provider": "Allora Testnet"
        }
    ],
    "sdk_version": "0.34.27",
    "coin_type": "118",
    "min_tx_fee": "800",
    "assets": [{
        "base": "uAllo",
        "symbol": "ALLO",
        "exponent": "6",
        "coingecko_id": "", 
        "logo": "https://raw.githubusercontent.com/batuoc263/t4e-explorer/master/src/assets/images/chain-logo/allora.jpeg"
    }],
    "addr_prefix": "allo",
	"coinType": 118,
	"bech32Config": {
		"bech32PrefixAccAddr": "allo",
		"bech32PrefixAccPub": "allopub",
		"bech32PrefixValAddr": "allovaloper",
		"bech32PrefixValPub": "allovaloperpub",
		"bech32PrefixConsAddr": "allovalcons",
		"bech32PrefixConsPub": "allovalconspub"
	},
    "theme_color": "#3FA263",
    "logo": "https://raw.githubusercontent.com/batuoc263/t4e-explorer/master/src/assets/images/chain-logo/allora.jpeg"
}
